[{"goodsid":"109848588","title":"全棉中老年男士休闲裤","price":"199","currentprice":"99","imgurl":"./img/1.jpg"},{"goodsid":"193542766","title":"花花公子休闲运动套装","price":"398","currentprice":"99","imgurl":"./img/2.jpg"},{"goodsid":"189847582","title":"盘扣刺绣太极唐装套装","price":"198","currentprice":"109","imgurl":"./img/3.jpg"},{"goodsid":"113547766","title":"花花公子男士夹克","price":"298","currentprice":"99","imgurl":"./img/4.jpg"},{"goodsid":"179849583","title":"英伦时尚休闲毛呢西装","price":"298","currentprice":"109","imgurl":"./img/5.jpg"},{"goodsid":"104545362","title":"花花公子男士休闲裤","price":"298","currentprice":"79","imgurl":"./img/6.jpg"},{"goodsid":"139842585","title":"休闲亚麻西服薄外套","price":"298","currentprice":"89","imgurl":"./img/7.jpg"},{"goodsid":"114548163","title":"花花公子休闲牛仔裤男","price":"298","currentprice":"79","imgurl":"./img/8.jpg"},{"goodsid":"149845587","title":"唐装刺绣套装短袖上衣","price":"299","currentprice":"109","imgurl":"./img/9.jpg"},{"goodsid":"184549560","title":"花花公子工装休闲裤男","price":"298","currentprice":"79","imgurl":"./img/10.jpg"},{"goodsid":"169846588","title":"唐装粗麻刺绣短袖套装","price":"399","currentprice":"249","imgurl":"./img/11.jpg"},{"goodsid":"175249488","title":"花花公子纯棉印花T恤","price":"398","currentprice":"29","imgurl":"./img/12.jpg"},{"goodsid":"119842489","title":"亚麻唐装短袖套装","price":"399","currentprice":"169","imgurl":"./img/13.jpg"},{"goodsid":"145247683","title":"花花公子清爽夏季短袖","price":"398","currentprice":"29","imgurl":"./img/14.jpg"},{"goodsid":"159848582","title":"唐装盘扣刺绣立领衬衣","price":"199","currentprice":"149","imgurl":"./img/15.jpg"},{"goodsid":"144545263","title":"花花公子男士纯棉长袖","price":"298","currentprice":"29","imgurl":"./img/16.jpg"},{"goodsid":"149840584","title":"棉麻盘扣套装亚麻唐装","price":"299","currentprice":"189","imgurl":"./img/17.jpg"},{"goodsid":"173544965","title":"花花公子男士纯棉长袖","price":"298","currentprice":"29","imgurl":"./img/18.jpg"},{"goodsid":"159843586","title":"82%亚麻纯色西服单西","price":"199","currentprice":"89","imgurl":"./img/19.jpg"},{"goodsid":"115248683","title":"花花公子潮牌休闲T恤","price":"398","currentprice":"29","imgurl":"./img/20.jpg"},{"goodsid":"119846587","title":"商务休闲男士单西外套","price":"299","currentprice":"99","imgurl":"./img/21.jpg"},{"goodsid":"165248885","title":"花花公子圆领休闲短袖","price":"398","currentprice":"29","imgurl":"./img/22.jpg"},{"goodsid":"139847588","title":"商务休闲西装上衣外套","price":"299","currentprice":"99","imgurl":"./img/23.jpg"},{"goodsid":"175243788","title":"花花公子男士百搭T恤","price":"398","currentprice":"29","imgurl":"./img/24.jpg"},{"goodsid":"129849589","title":"商务休闲百搭西装外套","price":"299","currentprice":"109","imgurl":"./img/25.jpg"},{"goodsid":"193544964","title":"花花公子男士纯棉长袖","price":"298","currentprice":"29","imgurl":"./img/26.jpg"},{"goodsid":"189842489","title":"51.6%羊毛英伦西装","price":"299","currentprice":"109","imgurl":"./img/27.jpg"},{"goodsid":"174548063","title":"花花公子男士纯棉长袖","price":"298","currentprice":"29","imgurl":"./img/28.jpg"},{"goodsid":"149845580","title":"休闲长袖修身西服外套","price":"299","currentprice":"109","imgurl":"./img/29.jpg"},{"goodsid":"184541163","title":"花花公子男士夹克","price":"398","currentprice":"99","imgurl":"./img/30.jpg"},{"goodsid":"169846581","title":"商务简约时尚修身西装","price":"299","currentprice":"139","imgurl":"./img/31.jpg"},{"goodsid":"134546262","title":"花花公子男士夹克","price":"398","currentprice":"109","imgurl":"./img/32.jpg"},{"goodsid":"129849582","title":"休闲修身长袖西装外套","price":"299","currentprice":"159","imgurl":"./img/33.jpg"},{"goodsid":"144549361","title":"花花公子长袖衬衫男","price":"298","currentprice":"79","imgurl":"./img/34.jpg"},{"goodsid":"119841584","title":"休闲修身长袖西服外套","price":"299","currentprice":"109","imgurl":"./img/35.jpg"},{"goodsid":"184541461","title":"花花公子长袖衬衫男","price":"298","currentprice":"79","imgurl":"./img/36.jpg"},{"goodsid":"109843585","title":"微弹修身休闲西装外套","price":"299","currentprice":"99","imgurl":"./img/37.jpg"},{"goodsid":"194544560","title":"花花公子秋季卫衣套装","price":"398","currentprice":"99","imgurl":"./img/38.jpg"},{"goodsid":"129844586","title":"中老年男士直筒西裤","price":"199","currentprice":"99","imgurl":"./img/39.jpg"},{"goodsid":"143549765","title":"花花公子男士卫衣套装","price":"398","currentprice":"99","imgurl":"./img/40.jpg"},{"goodsid":"199849589","title":"中老年男薄款棉休闲裤","price":"199","currentprice":"99","imgurl":"./img/41.jpg"},{"goodsid":"153542865","title":"花花公子弹力牛仔裤男","price":"398","currentprice":"99","imgurl":"./img/42.jpg"},{"goodsid":"159843489","title":"春夏男士薄款休闲长裤","price":"189","currentprice":"89","imgurl":"./img/43.jpg"},{"goodsid":"163545964","title":"花花公子休闲牛仔裤男","price":"398","currentprice":"99","imgurl":"./img/44.jpg"},{"goodsid":"119846580","title":"中老年男士薄款长西裤","price":"189","currentprice":"89","imgurl":"./img/45.jpg"},{"goodsid":"144549063","title":"花花公子男士拼接卫衣","price":"398","currentprice":"89","imgurl":"./img/46.jpg"},{"goodsid":"139847581","title":"中老年冰丝宽松T恤","price":"199","currentprice":"89","imgurl":"./img/47.jpg"},{"goodsid":"154542163","title":"花花公子男士圆领卫衣","price":"398","currentprice":"89","imgurl":"./img/48.jpg"},{"goodsid":"189841584","title":"男士商务冰丝宽松T恤","price":"199","currentprice":"89","imgurl":"./img/49.jpg"},{"goodsid":"104547262","title":"花花公子男士圆领卫衣","price":"398","currentprice":"89","imgurl":"./img/50.jpg"},{"goodsid":"179843585","title":"男士商务冰丝宽松T恤","price":"199","currentprice":"89","imgurl":"./img/51.jpg"},{"goodsid":"164545560","title":"花花公子圆领长袖卫衣","price":"398","currentprice":"89","imgurl":"./img/52.jpg"},{"goodsid":"199844586","title":"男士商务冰丝宽松T恤","price":"199","currentprice":"89","imgurl":"./img/53.jpg"},{"goodsid":"143548666","title":"花花公子时尚圆领卫衣","price":"398","currentprice":"69","imgurl":"./img/54.jpg"},{"goodsid":"169840680","title":"男士商务冰丝宽松T恤","price":"199","currentprice":"89","imgurl":"./img/55.jpg"},{"goodsid":"113540766","title":"花花公子青春时尚卫衣","price":"398","currentprice":"69","imgurl":"./img/56.jpg"},{"goodsid":"129844489","title":"男士商务冰丝宽松T恤","price":"199","currentprice":"89","imgurl":"./img/57.jpg"},{"goodsid":"123543865","title":"花花公子连帽休闲卫衣","price":"398","currentprice":"79","imgurl":"./img/58.jpg"},{"goodsid":"199849582","title":"中老年唐装棉麻套装","price":"199","currentprice":"69","imgurl":"./img/59.jpg"},{"goodsid":"133546964","title":"花花公子简约休闲卫衣","price":"398","currentprice":"69","imgurl":"./img/60.jpg"},{"goodsid":"159842584","title":"爷爷装短袖唐装套装","price":"199","currentprice":"169","imgurl":"./img/61.jpg"},{"goodsid":"114540064","title":"花花公子运动休闲卫衣","price":"398","currentprice":"69","imgurl":"./img/62.jpg"},{"goodsid":"149844585","title":"口袋绣花短袖唐装","price":"199","currentprice":"99","imgurl":"./img/63.jpg"},{"goodsid":"124543163","title":"花花公子舒适透气卫衣","price":"398","currentprice":"89","imgurl":"./img/64.jpg"},{"goodsid":"169845586","title":"粗麻加厚短袖唐装套装","price":"299","currentprice":"219","imgurl":"./img/65.jpg"},{"goodsid":"174547262","title":"花花公子新款百搭卫衣","price":"398","currentprice":"89","imgurl":"./img/66.jpg"},{"goodsid":"189846587","title":"长袖棉麻唐装套装","price":"199","currentprice":"119","imgurl":"./img/67.jpg"},{"goodsid":"114540362","title":"花花公子时尚经典卫衣","price":"398","currentprice":"79","imgurl":"./img/68.jpg"},{"goodsid":"179848588","title":"棉麻短袖唐装套装","price":"199","currentprice":"169","imgurl":"./img/69.jpg"},{"goodsid":"154542461","title":"花花公子时尚连帽卫衣","price":"398","currentprice":"89","imgurl":"./img/70.jpg"},{"goodsid":"199844489","title":"棉麻短袖唐装套装","price":"199","currentprice":"169","imgurl":"./img/71.jpg"},{"goodsid":"134546560","title":"花花公子拼接休闲卫衣","price":"398","currentprice":"89","imgurl":"./img/72.jpg"},{"goodsid":"189846580","title":"棉麻长袖唐装套装","price":"199","currentprice":"179","imgurl":"./img/73.jpg"},{"goodsid":"113549666","title":"花花公子圆领休闲卫衣","price":"398","currentprice":"89","imgurl":"./img/74.jpg"},{"goodsid":"109848581","title":"竹叶棉麻长袖唐装套装","price":"199","currentprice":"109","imgurl":"./img/75.jpg"},{"goodsid":"183540766","title":"花花公子男士时尚卫衣","price":"398","currentprice":"79","imgurl":"./img/76.jpg"},{"goodsid":"149849588","title":"四面高弹力休闲裤","price":"199","currentprice":"99","imgurl":"./img/77.jpg"},{"goodsid":"193543865","title":"花花公子时尚百搭卫衣","price":"398","currentprice":"79","imgurl":"./img/78.jpg"},{"goodsid":"139841680","title":"加厚斜纹休闲裤","price":"199","currentprice":"118","imgurl":"./img/79.jpg"},{"goodsid":"103547964","title":"花花公子简约舒适卫衣","price":"398","currentprice":"79","imgurl":"./img/80.jpg"},{"goodsid":"169845489","title":"中老年长袖针织打底衫","price":"199","currentprice":"139","imgurl":"./img/81.jpg"},{"goodsid":"184540064","title":"花花公子男士圆领卫衣","price":"398","currentprice":"79","imgurl":"./img/82.jpg"},{"goodsid":"159847580","title":"秋款长袖t恤针织衫男","price":"199","currentprice":"139","imgurl":"./img/83.jpg"},{"goodsid":"194543163","title":"花花公子男士长袖卫衣","price":"398","currentprice":"89","imgurl":"./img/84.jpg"},{"goodsid":"179848581","title":"中年男士长袖针织衫秋","price":"199","currentprice":"139","imgurl":"./img/85.jpg"},{"goodsid":"144548262","title":"花花公子男士圆领卫衣","price":"398","currentprice":"89","imgurl":"./img/86.jpg"},{"goodsid":"169840583","title":"春秋款圆领针织打底衫","price":"199","currentprice":"139","imgurl":"./img/87.jpg"},{"goodsid":"184540362","title":"花花公子男士圆领卫衣","price":"398","currentprice":"89","imgurl":"./img/88.jpg"},{"goodsid":"129843584","title":"中年爸爸针织打底衫T","price":"199","currentprice":"139","imgurl":"./img/89.jpg"},{"goodsid":"124543461","title":"花花公子男士圆领卫衣","price":"398","currentprice":"89","imgurl":"./img/90.jpg"},{"goodsid":"139846586","title":"春秋印花商务夹克","price":"299","currentprice":"129","imgurl":"./img/91.jpg"},{"goodsid":"183549666","title":"花花公子开衫外套男","price":"398","currentprice":"99","imgurl":"./img/92.jpg"},{"goodsid":"159847587","title":"瘦子专选套装休闲西装","price":"998","currentprice":"329","imgurl":"./img/93.jpg"},{"goodsid":"153541766","title":"花花公子男士夹克","price":"398","currentprice":"109","imgurl":"./img/94.jpg"},{"goodsid":"119840589","title":"商务正装西装礼服套装","price":"499","currentprice":"329","imgurl":"./img/95.jpg"},{"goodsid":"163544865","title":"花花公子男士夹克","price":"398","currentprice":"99","imgurl":"./img/96.jpg"},{"goodsid":"109842680","title":"羊毛呢拼色休闲小西装","price":"299","currentprice":"99","imgurl":"./img/97.jpg"},{"goodsid":"173547964","title":"花花公子男士夹克","price":"398","currentprice":"89","imgurl":"./img/98.jpg"},{"goodsid":"139846489","title":"加绒加厚商务衬衫","price":"199","currentprice":"89","imgurl":"./img/99.jpg"},{"goodsid":"154541064","title":"花花公子男士夹克","price":"398","currentprice":"99","imgurl":"./img/100.jpg"},{"goodsid":"164544163","title":"花花公子男士夹克","price":"398","currentprice":"99","imgurl":"./img/101.jpg"},{"goodsid":"114549262","title":"花花公子男士夹克外套","price":"398","currentprice":"99","imgurl":"./img/102.jpg"},{"goodsid":"154541362","title":"花花公子棒球领夹克男","price":"398","currentprice":"89","imgurl":"./img/103.jpg"},{"goodsid":"194543461","title":"花花公子连帽夹克外套","price":"398","currentprice":"99","imgurl":"./img/104.jpg"},{"goodsid":"134545163","title":"花花公子秋灯芯绒男裤","price":"398","currentprice":"99","imgurl":"./img/105.jpg"},{"goodsid":"184549262","title":"花花公子男灯芯绒长裤","price":"398","currentprice":"99","imgurl":"./img/106.jpg"},{"goodsid":"124542362","title":"花花公子束脚哈伦裤男","price":"398","currentprice":"89","imgurl":"./img/107.jpg"},{"goodsid":"164544461","title":"花花公子磨毛休闲裤男","price":"398","currentprice":"89","imgurl":"./img/108.jpg"},{"goodsid":"104547560","title":"花花公子修身小脚裤男","price":"398","currentprice":"89","imgurl":"./img/109.jpg"},{"goodsid":"153540667","title":"花花公子小脚牛仔裤潮","price":"398","currentprice":"99","imgurl":"./img/110.jpg"},{"goodsid":"123542766","title":"花花公子小脚牛仔裤男","price":"398","currentprice":"99","imgurl":"./img/111.jpg"},{"goodsid":"133545865","title":"花花公子弹力牛仔裤男","price":"398","currentprice":"99","imgurl":"./img/112.jpg"},{"goodsid":"143548964","title":"花花公子男士牛仔裤男","price":"398","currentprice":"99","imgurl":"./img/113.jpg"},{"goodsid":"124542064","title":"花花公子小脚牛仔裤男","price":"398","currentprice":"99","imgurl":"./img/114.jpg"},{"goodsid":"104546163","title":"花花公子弹力牛仔裤男","price":"398","currentprice":"99","imgurl":"./img/115.jpg"},{"goodsid":"154540263","title":"花花公子小脚牛仔裤男","price":"398","currentprice":"99","imgurl":"./img/116.jpg"},{"goodsid":"194542362","title":"花花公子男士牛仔裤男","price":"398","currentprice":"99","imgurl":"./img/117.jpg"},{"goodsid":"134545461","title":"花花公子男士牛仔裤","price":"398","currentprice":"99","imgurl":"./img/118.jpg"},{"goodsid":"174547560","title":"花花公子纯色牛仔裤男","price":"398","currentprice":"99","imgurl":"./img/119.jpg"},{"goodsid":"124541263","title":"花花公子卫衣长裤套装","price":"398","currentprice":"99","imgurl":"./img/120.jpg"},{"goodsid":"164543362","title":"花花公子卫衣长裤套装","price":"398","currentprice":"99","imgurl":"./img/121.jpg"},{"goodsid":"104546461","title":"花花公子圆领卫衣套装","price":"398","currentprice":"99","imgurl":"./img/122.jpg"},{"goodsid":"144548560","title":"花花公子休闲卫衣套装","price":"398","currentprice":"99","imgurl":"./img/123.jpg"},{"goodsid":"123541667","title":"花花公子男士长袖套装","price":"398","currentprice":"99","imgurl":"./img/124.jpg"},{"goodsid":"103546865","title":"花花公子百搭卫衣套装","price":"398","currentprice":"99","imgurl":"./img/125.jpg"},{"goodsid":"113549964","title":"花花公子时尚印花套装","price":"398","currentprice":"99","imgurl":"./img/126.jpg"},{"goodsid":"134544362","title":"花花公子拼接连帽卫衣","price":"398","currentprice":"79","imgurl":"./img/127.jpg"},{"goodsid":"174546461","title":"花花公子拼接连帽卫衣","price":"398","currentprice":"79","imgurl":"./img/128.jpg"},{"goodsid":"114549560","title":"花花公子拼接连帽卫衣","price":"398","currentprice":"79","imgurl":"./img/129.jpg"},{"goodsid":"193541667","title":"花花公子拼接连帽卫衣","price":"398","currentprice":"79","imgurl":"./img/130.jpg"},{"goodsid":"163543766","title":"花花公子拼接连帽卫衣","price":"398","currentprice":"79","imgurl":"./img/131.jpg"},{"goodsid":"173546865","title":"花花公子拼接连帽卫衣","price":"398","currentprice":"79","imgurl":"./img/132.jpg"},{"goodsid":"183549964","title":"花花公子拼接连帽卫衣","price":"398","currentprice":"79","imgurl":"./img/133.jpg"},{"goodsid":"194542064","title":"花花公子拼接连帽卫衣","price":"398","currentprice":"79","imgurl":"./img/134.jpg"},{"goodsid":"174546163","title":"花花公子拼接连帽卫衣","price":"398","currentprice":"79","imgurl":"./img/135.jpg"},{"goodsid":"194541263","title":"花花公子拼接连帽卫衣","price":"398","currentprice":"79","imgurl":"./img/136.jpg"},{"goodsid":"133544766","title":"花花公子男士工装裤","price":"298","currentprice":"69","imgurl":"./img/137.jpg"},{"goodsid":"143547865","title":"花花公子男士工装裤","price":"298","currentprice":"69","imgurl":"./img/138.jpg"},{"goodsid":"153540965","title":"花花公子男士工装裤","price":"298","currentprice":"69","imgurl":"./img/139.jpg"},{"goodsid":"164543064","title":"花花公子男士工装裤","price":"298","currentprice":"69","imgurl":"./img/140.jpg"},{"goodsid":"144547163","title":"花花公子男士工装裤","price":"298","currentprice":"69","imgurl":"./img/141.jpg"},{"goodsid":"164542263","title":"花花公子男士工装裤","price":"298","currentprice":"79","imgurl":"./img/142.jpg"},{"goodsid":"144547461","title":"花花公子男士工装裤","price":"298","currentprice":"69","imgurl":"./img/143.jpg"},{"goodsid":"163542667","title":"花花公子小脚牛仔裤男","price":"298","currentprice":"79","imgurl":"./img/144.jpg"},{"goodsid":"103545766","title":"花花公子束脚牛仔裤男","price":"298","currentprice":"79","imgurl":"./img/145.jpg"},{"goodsid":"113548865","title":"花花公子渐变牛仔裤男","price":"298","currentprice":"79","imgurl":"./img/146.jpg"},{"goodsid":"123541965","title":"花花公子韩版牛仔裤男","price":"298","currentprice":"79","imgurl":"./img/147.jpg"},{"goodsid":"134544064","title":"花花公子潮流牛仔裤男","price":"298","currentprice":"79","imgurl":"./img/148.jpg"},{"goodsid":"134543263","title":"花花公子时尚牛仔裤男","price":"298","currentprice":"79","imgurl":"./img/149.jpg"},{"goodsid":"154540561","title":"花花公子长袖格子衬衫","price":"298","currentprice":"79","imgurl":"./img/150.jpg"},{"goodsid":"133543667","title":"花花公子长袖格子衬衫","price":"298","currentprice":"79","imgurl":"./img/151.jpg"},{"goodsid":"173545766","title":"花花公子长袖格子衬衫","price":"298","currentprice":"79","imgurl":"./img/152.jpg"},{"goodsid":"183548865","title":"花花公子长袖衬衫男","price":"298","currentprice":"79","imgurl":"./img/153.jpg"},{"goodsid":"193541965","title":"花花公子长袖衬衫男","price":"298","currentprice":"79","imgurl":"./img/154.jpg"},{"goodsid":"104545064","title":"花花公子长袖衬衫男","price":"298","currentprice":"79","imgurl":"./img/155.jpg"},{"goodsid":"184548163","title":"花花公子长袖衬衫男","price":"298","currentprice":"79","imgurl":"./img/156.jpg"},{"goodsid":"104544263","title":"花花公子长袖衬衫男","price":"298","currentprice":"79","imgurl":"./img/157.jpg"},{"goodsid":"174545362","title":"花花公子长袖衬衫男","price":"298","currentprice":"79","imgurl":"./img/158.jpg"},{"goodsid":"114548461","title":"花花公子长袖衬衫男","price":"298","currentprice":"79","imgurl":"./img/159.jpg"},{"goodsid":"124541561","title":"花花公子长袖衬衫男","price":"298","currentprice":"79","imgurl":"./img/160.jpg"},{"goodsid":"103544667","title":"花花公子长袖衬衫男","price":"298","currentprice":"79","imgurl":"./img/161.jpg"},{"goodsid":"143546766","title":"花花公子长袖衬衫男","price":"298","currentprice":"79","imgurl":"./img/162.jpg"},{"goodsid":"153549865","title":"花花公子长袖衬衫男","price":"298","currentprice":"79","imgurl":"./img/163.jpg"},{"goodsid":"154549163","title":"花花公子长袖卫衣男","price":"298","currentprice":"79","imgurl":"./img/164.jpg"},{"goodsid":"194541561","title":"花花公子男士夹克","price":"298","currentprice":"99","imgurl":"./img/165.jpg"},{"goodsid":"173544667","title":"花花公子男士夹克","price":"298","currentprice":"99","imgurl":"./img/166.jpg"},{"goodsid":"123540866","title":"花花公子男士夹克","price":"298","currentprice":"99","imgurl":"./img/167.jpg"},{"goodsid":"144546362","title":"花花公子纯棉长袖","price":"398","currentprice":"29","imgurl":"./img/168.jpg"},{"goodsid":"184548461","title":"花花公子纯棉长袖","price":"398","currentprice":"29","imgurl":"./img/169.jpg"},{"goodsid":"164542561","title":"花花公子纯棉长袖","price":"398","currentprice":"29","imgurl":"./img/170.jpg"},{"goodsid":"143545667","title":"花花公子纯棉长袖","price":"398","currentprice":"29","imgurl":"./img/171.jpg"},{"goodsid":"183547766","title":"花花公子纯棉长袖","price":"398","currentprice":"29","imgurl":"./img/172.jpg"},{"goodsid":"193540866","title":"花花公子纯棉长袖","price":"398","currentprice":"29","imgurl":"./img/173.jpg"},{"goodsid":"163542965","title":"花花公子纯棉长袖","price":"398","currentprice":"29","imgurl":"./img/174.jpg"},{"goodsid":"174545064","title":"花花公子纯棉长袖","price":"398","currentprice":"29","imgurl":"./img/175.jpg"},{"goodsid":"124540164","title":"花花公子纯棉长袖","price":"398","currentprice":"29","imgurl":"./img/176.jpg"},{"goodsid":"174544263","title":"花花公子纯棉长袖","price":"398","currentprice":"29","imgurl":"./img/177.jpg"},{"goodsid":"114547362","title":"花花公子纯棉长袖","price":"398","currentprice":"29","imgurl":"./img/178.jpg"},{"goodsid":"154549461","title":"花花公子纯棉长袖","price":"398","currentprice":"29","imgurl":"./img/179.jpg"},{"goodsid":"134543561","title":"花花公子纯棉长袖","price":"398","currentprice":"29","imgurl":"./img/180.jpg"},{"goodsid":"113546667","title":"花花公子纯棉长袖","price":"398","currentprice":"29","imgurl":"./img/181.jpg"},{"goodsid":"153548766","title":"花花公子纯棉长袖","price":"398","currentprice":"29","imgurl":"./img/182.jpg"},{"goodsid":"163541866","title":"花花公子纯棉长袖","price":"398","currentprice":"29","imgurl":"./img/183.jpg"},{"goodsid":"133543965","title":"花花公子纯棉长袖","price":"398","currentprice":"29","imgurl":"./img/184.jpg"},{"goodsid":"144546064","title":"花花公子纯棉长袖","price":"398","currentprice":"29","imgurl":"./img/185.jpg"},{"goodsid":"194540164","title":"花花公子男士纯棉长袖","price":"298","currentprice":"29","imgurl":"./img/186.jpg"},{"goodsid":"184547362","title":"花花公子男士纯棉长袖","price":"298","currentprice":"29","imgurl":"./img/187.jpg"},{"goodsid":"124540462","title":"花花公子男士纯棉长袖","price":"298","currentprice":"29","imgurl":"./img/188.jpg"},{"goodsid":"104544561","title":"花花公子男士纯棉长袖","price":"298","currentprice":"29","imgurl":"./img/189.jpg"},{"goodsid":"183546667","title":"花花公子男士纯棉长袖","price":"298","currentprice":"29","imgurl":"./img/190.jpg"},{"goodsid":"123549766","title":"花花公子男士纯棉长袖","price":"298","currentprice":"29","imgurl":"./img/191.jpg"},{"goodsid":"133542866","title":"花花公子男士纯棉长袖","price":"298","currentprice":"29","imgurl":"./img/192.jpg"},{"goodsid":"103544965","title":"花花公子男士纯棉长袖","price":"298","currentprice":"29","imgurl":"./img/193.jpg"},{"goodsid":"114547064","title":"花花公子男士纯棉长袖","price":"298","currentprice":"29","imgurl":"./img/194.jpg"},{"goodsid":"164541164","title":"花花公子男士纯棉长袖","price":"298","currentprice":"29","imgurl":"./img/195.jpg"},{"goodsid":"114546263","title":"花花公子男士纯棉长袖","price":"298","currentprice":"29","imgurl":"./img/196.jpg"},{"goodsid":"154548362","title":"花花公子男士纯棉长袖","price":"298","currentprice":"29","imgurl":"./img/197.jpg"},{"goodsid":"194540462","title":"花花公子男士纯棉长袖","price":"298","currentprice":"29","imgurl":"./img/198.jpg"},{"goodsid":"174544561","title":"花花公子男士纯棉长袖","price":"298","currentprice":"29","imgurl":"./img/199.jpg"},{"goodsid":"153547667","title":"花花公子男士纯棉长袖","price":"298","currentprice":"29","imgurl":"./img/200.jpg"},{"goodsid":"193549766","title":"花花公子男士纯棉长袖","price":"298","currentprice":"29","imgurl":"./img/201.jpg"},{"goodsid":"103543866","title":"花花公子男士纯棉长袖","price":"298","currentprice":"29","imgurl":"./img/202.jpg"},{"goodsid":"184547064","title":"花花公子男士纯棉长袖","price":"298","currentprice":"29","imgurl":"./img/203.jpg"},{"goodsid":"134542164","title":"花花公子男士纯棉长袖","price":"298","currentprice":"29","imgurl":"./img/204.jpg"},{"goodsid":"184546263","title":"花花公子男士纯棉长袖","price":"298","currentprice":"29","imgurl":"./img/205.jpg"},{"goodsid":"124549362","title":"花花公子男士卫衣套装","price":"398","currentprice":"99","imgurl":"./img/206.jpg"},{"goodsid":"164541462","title":"花花公子男士卫衣套装","price":"398","currentprice":"99","imgurl":"./img/207.jpg"},{"goodsid":"144545561","title":"花花公子男士卫衣套装","price":"398","currentprice":"99","imgurl":"./img/208.jpg"},{"goodsid":"123548667","title":"花花公子连帽卫衣套装","price":"398","currentprice":"99","imgurl":"./img/209.jpg"},{"goodsid":"163540767","title":"花花公子男士卫衣套装","price":"398","currentprice":"99","imgurl":"./img/210.jpg"},{"goodsid":"173543866","title":"花花公子男士开衫外套","price":"398","currentprice":"99","imgurl":"./img/211.jpg"},{"goodsid":"143545965","title":"花花公子男士开衫外套","price":"398","currentprice":"99","imgurl":"./img/212.jpg"},{"goodsid":"154548064","title":"花花公子男士圆领卫衣","price":"398","currentprice":"89","imgurl":"./img/213.jpg"},{"goodsid":"104543164","title":"花花公子男士拼接卫衣","price":"398","currentprice":"89","imgurl":"./img/214.jpg"},{"goodsid":"155241286","title":"花花公子时尚纯棉短袖","price":"398","currentprice":"29","imgurl":"./img/215.jpg"},{"goodsid":"185247383","title":"花花公子夏季纯棉短袖","price":"398","currentprice":"29","imgurl":"./img/216.jpg"},{"goodsid":"185244481","title":"花花公子纯棉印花短袖","price":"398","currentprice":"29","imgurl":"./img/217.jpg"},{"goodsid":"105249488","title":"花花公子薄款纯棉短袖","price":"398","currentprice":"29","imgurl":"./img/218.jpg"},{"goodsid":"125243586","title":"花花公子透气百搭短袖","price":"398","currentprice":"29","imgurl":"./img/219.jpg"},{"goodsid":"175246683","title":"花花公子小标印花T恤","price":"398","currentprice":"29","imgurl":"./img/220.jpg"},{"goodsid":"115248780","title":"花花公子绣花胸标T恤","price":"398","currentprice":"29","imgurl":"./img/221.jpg"},{"goodsid":"135242788","title":"花花公子透气舒适T恤","price":"398","currentprice":"29","imgurl":"./img/222.jpg"},{"goodsid":"125247885","title":"花花公子纯棉透气T恤","price":"398","currentprice":"29","imgurl":"./img/223.jpg"},{"goodsid":"115242983","title":"花花公子男士纯棉T恤","price":"398","currentprice":"29","imgurl":"./img/224.jpg"},{"goodsid":"125242286","title":"花花公子清爽百搭T恤","price":"398","currentprice":"29","imgurl":"./img/225.jpg"},{"goodsid":"155248383","title":"花花公子清爽百搭短袖","price":"398","currentprice":"29","imgurl":"./img/226.jpg"},{"goodsid":"155245481","title":"花花公子纯棉百搭短袖","price":"398","currentprice":"29","imgurl":"./img/227.jpg"},{"goodsid":"195243586","title":"花花公子潮流纯棉T恤","price":"398","currentprice":"29","imgurl":"./img/228.jpg"},{"goodsid":"185248780","title":"花花公子100%纯棉T恤","price":"298","currentprice":"29","imgurl":"./img/229.jpg"},{"goodsid":"105243788","title":"花花公子时尚休闲T恤","price":"298","currentprice":"29","imgurl":"./img/230.jpg"},{"goodsid":"195247885","title":"花花公子品质纯棉T恤","price":"298","currentprice":"29","imgurl":"./img/231.jpg"},{"goodsid":"185242983","title":"花花公子舒适纯棉短t","price":"298","currentprice":"29","imgurl":"./img/232.jpg"},{"goodsid":"195242286","title":"花花公子舒适纯棉T恤","price":"298","currentprice":"29","imgurl":"./img/233.jpg"},{"goodsid":"125249383","title":"花花公子短袖T恤男装","price":"398","currentprice":"29","imgurl":"./img/234.jpg"},{"goodsid":"125246481","title":"花花公子纯棉短袖T恤","price":"398","currentprice":"29","imgurl":"./img/235.jpg"},{"goodsid":"145240489","title":"花花公子纯棉短袖男装","price":"398","currentprice":"29","imgurl":"./img/236.jpg"},{"goodsid":"165244586","title":"花花公子绣标T恤男装","price":"398","currentprice":"29","imgurl":"./img/237.jpg"},{"goodsid":"155249780","title":"花花公子夏季新款短袖","price":"398","currentprice":"29","imgurl":"./img/238.jpg"},{"goodsid":"155243983","title":"花花公子纯棉百搭T恤","price":"398","currentprice":"29","imgurl":"./img/239.jpg"},{"goodsid":"165243286","title":"花花公子男士印花T恤","price":"398","currentprice":"29","imgurl":"./img/240.jpg"}]